TQapis/TQAPIUtilities.py
TQapis/TQConnection.py
TQapis/TQRequests.py
TQapis/TQResponse.py
TQapis/TQTest.py
TQapis/__init__.py
TQapis-0.12.7.dist-info/LICENSE.txt
TQapis-0.12.7.dist-info/METADATA
TQapis-0.12.7.dist-info/WHEEL
TQapis-0.12.7.dist-info/top_level.txt
TQapis-0.12.7.dist-info/RECORD
