Metadata-Version: 2.1
Name: TQapis
Version: 0.12.7
Summary: Python package providing a simple interface to support TreasuryQuants.com's http protocols
Home-page: https://github.com/treasuryquants/TQPython
Author: Shahram Alavian
Author-email: contact@treasuryquants.com
Maintainer: Tanmay Jain
Maintainer-email: tanmayjain.cs@gmail.com
License: MIT
Keywords: Treasury,Quant,TreasuryQuants,Swap,Valuations,Quantitative Finance
Platform: UNKNOWN
Requires-Dist: requests
